{
"persons": [ {
  "code" : "944c",
  "firstName" : "Starlin",
  "lastName" : "Castro",
  "address" : {
    "streetAddress" : "1060 West Addison Street",
    "city" : "Chicago",
    "state" : "IL",
    "zip" : "60613",
    "country" : "USA"
  },
  "emails" : [ "scastro@cubs.com", "starlin_castro13@gmail.com" ],
  "nameStringLF" : "Castro, Starlin"
}, {
  "code" : "306a",
  "firstName" : "Brock",
  "lastName" : "Sampson",
  "address" : {
    "streetAddress" : "123 N 1st Street",
    "city" : "Omaha",
    "state" : "NE",
    "zip" : "68116",
    "country" : "USA"
  },
  "emails" : [ "brock_f_sampson@gmail.com", "bsampson@venture.com" ],
  "nameStringLF" : "Sampson, Brock"
}, {
  "code" : "2342",
  "firstName" : "Miles",
  "lastName" : "O'Brien",
  "address" : {
    "streetAddress" : "123 Friendly Street",
    "city" : "Ottawa",
    "state" : "ON",
    "zip" : "K1A 0G9",
    "country" : "Canada"
  },
  "emails" : [ ],
  "nameStringLF" : "O'Brien, Miles"
}, {
  "code" : "aef1",
  "firstName" : "Gordon",
  "lastName" : "Gekko",
  "address" : {
    "streetAddress" : "1 Wall Street",
    "city" : "New York",
    "state" : "NY",
    "zip" : "10005-0012",
    "country" : "USA"
  },
  "emails" : [ ],
  "secID" : "sec001",
  "type" : "EXPERT",
  "nameStringLF" : "Gekko, Gordon"
}, {
  "code" : "321f",
  "firstName" : "Bud",
  "lastName" : "Fox",
  "address" : {
    "streetAddress" : "321 Bronx Street",
    "city" : "New York",
    "state" : "NY",
    "zip" : "10004",
    "country" : "USA"
  },
  "emails" : [ "bfox@gmail.com", "csheen@crazy.net" ],
  "secID" : "sec991",
  "type" : "JUNIOR",
  "nameStringLF" : "Fox, Bud"
}, {
  "code" : "ma12",
  "firstName" : "Dale",
  "lastName" : "Sveum",
  "address" : {
    "streetAddress" : "1060 West Addison Street",
    "city" : "Chicago",
    "state" : "IL",
    "zip" : "60613",
    "country" : "USA"
  },
  "emails" : [ "sveum@cubs.com" ],
  "nameStringLF" : "Sveum, Dale"
}, {
  "code" : "321nd",
  "firstName" : "William",
  "lastName" : "Hartnell",
  "address" : {
    "streetAddress" : "1060 West Addison Street",
    "city" : "Chicago",
    "state" : "IL",
    "zip" : "60613",
    "country" : "USA"
  },
  "emails" : [ "whartnell@doctors.com", "dr@who.com" ],
  "nameStringLF" : "Hartnell, William"
}, {
  "code" : "nf32a",
  "firstName" : "Patrick",
  "lastName" : "Troughton",
  "address" : {
    "streetAddress" : "1060 West Addison Street",
    "city" : "Chicago",
    "state" : "IL",
    "zip" : "60613",
    "country" : "USA"
  },
  "emails" : [ "ptroug@cse.unl.edu", "ptrou32@unl.edu" ],
  "nameStringLF" : "Troughton, Patrick"
}, {
  "code" : "321na",
  "firstName" : "Jon",
  "lastName" : "Pertwee",
  "address" : {
    "streetAddress" : "301 Front St W",
    "city" : " Toronto",
    "state" : " ON",
    "zip" : " M5V 2T6",
    "country" : " Canada"
  },
  "emails" : [ "jpet@whofan.com" ],
  "secID" : "sec125",
  "type" : "EXPERT",
  "nameStringLF" : "Pertwee, Jon"
}, {
  "code" : "231",
  "firstName" : "Tom",
  "lastName" : "Baker",
  "address" : {
    "streetAddress" : "1 Blue Jays Way",
    "city" : " Toronto",
    "state" : " ON",
    "zip" : " M5V 1J1",
    "country" : " Canada"
  },
  "emails" : [ "famousdoc@who.com", "tbaker@cse.unl.edu", "mostfamous@whovian.com", "thedoctor@bbc.com" ],
  "secID" : "sec221",
  "type" : "EXPERT",
  "nameStringLF" : "Baker, Tom"
}, {
  "code" : "6doc",
  "firstName" : "Richard",
  "lastName" : "Hurndall",
  "address" : {
    "streetAddress" : "Campos El290",
    "city" : "Mexico City",
    "state" : " FD",
    "zip" : "",
    "country" : " Mexico"
  },
  "emails" : [ "rhurndall@cse.unl.edu", "richard@unl.edu" ],
  "secID" : "sec982",
  "type" : "JUNIOR",
  "nameStringLF" : "Hurndall, Richard"
}, {
  "code" : "321dr",
  "firstName" : "C.",
  "lastName" : "Baker",
  "address" : {
    "streetAddress" : "Avery Hall",
    "city" : "Lincoln",
    "state" : "NE",
    "zip" : "68503",
    "country" : "USA"
  },
  "emails" : [ "dr@baker.com" ],
  "secID" : "sec543",
  "type" : "JUNIOR",
  "nameStringLF" : "Baker, C."
}, {
  "code" : "1svndr",
  "firstName" : "Sylvester",
  "lastName" : "McCoy",
  "address" : {
    "streetAddress" : "126-01 Roosevelt Ave",
    "city" : " Flushing",
    "state" : " NY",
    "zip" : "11368",
    "country" : "USA"
  },
  "emails" : [ "slyguy@hotmail.com", "mccoy@whofan.com" ],
  "nameStringLF" : "McCoy, Sylvester"
}, {
  "code" : "123lst",
  "firstName" : "Paul",
  "lastName" : "McGann",
  "address" : {
    "streetAddress" : "1 MetLife Stadium Dr",
    "city" : " East Rutherford",
    "state" : " NJ",
    "zip" : "07073",
    "country" : "USA"
  },
  "emails" : [ "pmcgann@mlb.com", "foo@bar.com", "pmc@unl.edu" ],
  "secID" : "sec31x",
  "type" : "EXPERT",
  "nameStringLF" : "McGann, Paul"
}, {
  "code" : "nwdoc1",
  "firstName" : "Chris",
  "lastName" : "Eccleston",
  "address" : {
    "streetAddress" : "1 E 161st St",
    "city" : " Bronx",
    "state" : " NY",
    "zip" : "10451",
    "country" : "USA"
  },
  "emails" : [ "newguy@whovian.com" ],
  "secID" : "sec953",
  "type" : "JUNIOR",
  "nameStringLF" : "Eccleston, Chris"
}, {
  "code" : "2ndbestd",
  "firstName" : "David",
  "lastName" : "Tennant",
  "address" : {
    "streetAddress" : "700 E Grand Ave",
    "city" : " Chicago",
    "state" : " IL",
    "zip" : " 60611",
    "country" : "USA"
  },
  "emails" : [ "actor@shakespeare.com", "tdavid@unl.edu" ],
  "nameStringLF" : "Tennant, David"
}, {
  "code" : "wrddoc",
  "firstName" : "Matt",
  "lastName" : "Smith",
  "address" : {
    "streetAddress" : "333 W 35th St",
    "city" : " Chicago",
    "state" : " IL",
    "zip" : "60616",
    "country" : "USA"
  },
  "emails" : [ "msmith@who.com", "thedoc@cse.unl.edu" ],
  "nameStringLF" : "Smith, Matt"
}, {
  "code" : "bbchar",
  "firstName" : "Kaylee",
  "lastName" : "Ehrmantraut",
  "address" : {
    "streetAddress" : "800 West 7th Street",
    "city" : " Albuquerque",
    "state" : " NM",
    "zip" : " 87105",
    "country" : "USA"
  },
  "emails" : [ ],
  "nameStringLF" : "Ehrmantraut, Kaylee"
}, {
  "code" : "doc05",
  "firstName" : "Peter",
  "lastName" : "Davison",
  "address" : {
    "streetAddress" : "123 Cabo San Lucas",
    "city" : " Los Cabos",
    "state" : " BCS",
    "zip" : " ",
    "country" : " Mexico"
  },
  "emails" : [ ],
  "nameStringLF" : "Davison, Peter"
} ]}
